README.md
setup.py
allthingsnlp/__init__.py
allthingsnlp/text_explorer.py
allthingsnlp/text_processor.py
allthingsnlp.egg-info/PKG-INFO
allthingsnlp.egg-info/SOURCES.txt
allthingsnlp.egg-info/dependency_links.txt
allthingsnlp.egg-info/requires.txt
allthingsnlp.egg-info/top_level.txt